MANIFEST.in
README.rst
setup.py
django_keyedcache.egg-info/PKG-INFO
django_keyedcache.egg-info/SOURCES.txt
django_keyedcache.egg-info/dependency_links.txt
django_keyedcache.egg-info/requires.txt
django_keyedcache.egg-info/top_level.txt
keyedcache/__init__.py
keyedcache/models.py
keyedcache/tests.py
keyedcache/tests_urls.py
keyedcache/threaded.py
keyedcache/urls.py
keyedcache/utils.py
keyedcache/views.py
keyedcache/locale/de/LC_MESSAGES/django.mo
keyedcache/locale/de/LC_MESSAGES/django.po
keyedcache/locale/en/LC_MESSAGES/django.mo
keyedcache/locale/en/LC_MESSAGES/django.po
keyedcache/locale/es/LC_MESSAGES/django.po
keyedcache/locale/fr/LC_MESSAGES/django.mo
keyedcache/locale/fr/LC_MESSAGES/django.po
keyedcache/locale/he/LC_MESSAGES/django.mo
keyedcache/locale/he/LC_MESSAGES/django.po
keyedcache/locale/it/LC_MESSAGES/django.mo
keyedcache/locale/it/LC_MESSAGES/django.po
keyedcache/locale/ko/LC_MESSAGES/django.mo
keyedcache/locale/ko/LC_MESSAGES/django.po
keyedcache/locale/pl/LC_MESSAGES/django.mo
keyedcache/locale/pl/LC_MESSAGES/django.po
keyedcache/locale/pt_BR/LC_MESSAGES/django.mo
keyedcache/locale/pt_BR/LC_MESSAGES/django.po
keyedcache/locale/ru/LC_MESSAGES/django.mo
keyedcache/locale/ru/LC_MESSAGES/django.po
keyedcache/locale/sv/LC_MESSAGES/django.mo
keyedcache/locale/sv/LC_MESSAGES/django.po
keyedcache/locale/tr/LC_MESSAGES/django.mo
keyedcache/locale/tr/LC_MESSAGES/django.po
keyedcache/templates/keyedcache/delete.html
keyedcache/templates/keyedcache/stats.html
keyedcache/templates/keyedcache/view.html