Metadata-Version: 1.1
Name: django-keyedcache
Version: 1.5.0
Summary: keyedcache
Home-page: http://bitbucket.org/bkroeze/django-keyedcache/
Author: Bruce Kroeze
Author-email: brucek@ecomsmith.com
License: New BSD License
Platform: any
Classifier: Development Status :: 4 - Beta
Classifier: Environment :: Web Environment
Classifier: Intended Audience :: Developers
Classifier: License :: OSI Approved :: BSD License
Classifier: Operating System :: OS Independent
Classifier: Programming Language :: Python
Classifier: Programming Language :: Python :: 2.5
Classifier: Programming Language :: Python :: 2.6
Classifier: Programming Language :: Python :: 2.7
Classifier: Framework :: Django
